pz_rail_pipelines-1.1.2.dist-info/licenses/LICENSE
rail/_pipelines/__init__.py
rail/_pipelines/_version.py
rail/pipelines/estimation/estimate_all.py
rail/pipelines/estimation/inform_all.py
rail/pipelines/estimation/pz_all.py
rail/pipelines/estimation/tomography.py
rail/pipelines/evaluation/evaluate_all.py
rail/pipelines/examples/goldenspike/goldenspike.py
rail/pipelines/examples/survey_nonuniformity/survey_nonuniformity.py
rail/pipelines/utils/prepare_observed.py
rail/utils/algo_library.py
pz_rail_pipelines-1.1.2.dist-info/METADATA
pz_rail_pipelines-1.1.2.dist-info/WHEEL
pz_rail_pipelines-1.1.2.dist-info/top_level.txt
pz_rail_pipelines-1.1.2.dist-info/RECORD
